fast_micro/__init__.py
fast_micro/constants.py
fast_micro/logger.py
fast_micro/middleware.py
fast_micro/models.py
fast_micro/permission.py
fast_micro/requests.py
fast_micro/utils.py
fast_micro-0.0.15.dist-info/METADATA
fast_micro-0.0.15.dist-info/WHEEL
fast_micro-0.0.15.dist-info/top_level.txt
fast_micro-0.0.15.dist-info/RECORD
